neural_pipeline/__init__.py
neural_pipeline/monitoring.py
neural_pipeline/predict.py
neural_pipeline/train.py
neural_pipeline/builtin/__init__.py
neural_pipeline/builtin/models/__init__.py
neural_pipeline/builtin/models/albunet.py
neural_pipeline/builtin/monitors/__init__.py
neural_pipeline/builtin/monitors/mpl.py
neural_pipeline/builtin/monitors/tensorboard.py
neural_pipeline/data_processor/__init__.py
neural_pipeline/data_processor/data_processor.py
neural_pipeline/data_processor/model.py
neural_pipeline/data_producer/__init__.py
neural_pipeline/data_producer/data_producer.py
neural_pipeline/train_config/__init__.py
neural_pipeline/train_config/train_config.py
neural_pipeline/utils/__init__.py
neural_pipeline/utils/file_structure_manager.py
neural_pipeline/utils/utils.py
neural_pipeline-0.1.0.dist-info/LICENSE
neural_pipeline-0.1.0.dist-info/METADATA
neural_pipeline-0.1.0.dist-info/WHEEL
neural_pipeline-0.1.0.dist-info/top_level.txt
neural_pipeline-0.1.0.dist-info/RECORD
