Metadata-Version: 2.1
Name: neural-pipeline
Version: 0.1.0
Summary: Neural networks training pipeline based on PyTorch. Designed to standardize training process and to increase coding preformance
Home-page: https://github.com/toodef/neural-pipeline
Author: Anton Fedotov
Author-email: anton.fedotov.af@gmail.com.com
License: UNKNOWN
Platform: UNKNOWN
Classifier: Development Status :: 3 - Alpha
Classifier: Programming Language :: Python :: 3
Classifier: License :: OSI Approved :: MIT License
Classifier: Intended Audience :: Developers
Classifier: Intended Audience :: Science/Research
Classifier: Operating System :: OS Independent
Classifier: Programming Language :: Python :: 3.5
Classifier: Programming Language :: Python :: 3.6
Classifier: Topic :: Scientific/Engineering
Classifier: Topic :: Scientific/Engineering :: Artificial Intelligence
Classifier: Topic :: Scientific/Engineering :: Image Recognition
Classifier: Topic :: Software Development :: Libraries
Classifier: Topic :: Software Development :: Libraries :: Python Modules
Requires-Dist: numpy
Requires-Dist: tqdm
Requires-Dist: torch (==0.4.1)
